autogalaxy/__init__.py
autogalaxy/abstract_fit.py
autogalaxy/convert.py
autogalaxy/exc.py
autogalaxy/fixtures.py
autogalaxy/mock.py
autogalaxy/aggregator/__init__.py
autogalaxy/aggregator/agg_util.py
autogalaxy/aggregator/dataset_model.py
autogalaxy/aggregator/galaxies.py
autogalaxy/aggregator/subplot.py
autogalaxy/aggregator/ellipse/__init__.py
autogalaxy/aggregator/ellipse/ellipses.py
autogalaxy/aggregator/ellipse/fit_ellipse.py
autogalaxy/aggregator/ellipse/multipoles.py
autogalaxy/aggregator/imaging/__init__.py
autogalaxy/aggregator/imaging/fit_imaging.py
autogalaxy/aggregator/imaging/imaging.py
autogalaxy/aggregator/interferometer/__init__.py
autogalaxy/aggregator/interferometer/fit_interferometer.py
autogalaxy/aggregator/interferometer/interferometer.py
autogalaxy/analysis/__init__.py
autogalaxy/analysis/chaining_util.py
autogalaxy/analysis/model_util.py
autogalaxy/analysis/plotter_interface.py
autogalaxy/analysis/result.py
autogalaxy/analysis/adapt_images/__init__.py
autogalaxy/analysis/adapt_images/adapt_images.py
autogalaxy/analysis/analysis/__init__.py
autogalaxy/analysis/analysis/analysis.py
autogalaxy/analysis/analysis/dataset.py
autogalaxy/analysis/mock/__init__.py
autogalaxy/analysis/mock/mock_result.py
autogalaxy/config/.gitignore
autogalaxy/config/README.rst
autogalaxy/config/general.yaml
autogalaxy/config/notation.yaml
autogalaxy/config/output.yaml
autogalaxy/config/priors/README.rst
autogalaxy/config/priors/basis.yaml
autogalaxy/config/priors/cosmology.yaml
autogalaxy/config/priors/dataset_model.yaml
autogalaxy/config/priors/point_sources.yaml
autogalaxy/config/priors/ellipse/README.rst
autogalaxy/config/priors/ellipse/ellipse.yaml
autogalaxy/config/priors/ellipse/ellipse_multipole.yaml
autogalaxy/config/priors/galaxy/README.rst
autogalaxy/config/priors/galaxy/redshift.yaml
autogalaxy/config/priors/light/README.rst
autogalaxy/config/priors/light/linear/chameleon.yaml
autogalaxy/config/priors/light/linear/dev_vaucouleurs.yaml
autogalaxy-2026.1.21.3.dist-info/licenses/LICENSE
autogalaxy-2026.1.21.3.dist-info/METADATA
autogalaxy-2026.1.21.3.dist-info/WHEEL
autogalaxy-2026.1.21.3.dist-info/top_level.txt
autogalaxy-2026.1.21.3.dist-info/RECORD
